whatubinup2/__init__.py
whatubinup2/__main__.py
whatubinup2-4.0.0.dist-info/METADATA
whatubinup2-4.0.0.dist-info/WHEEL
whatubinup2-4.0.0.dist-info/entry_points.txt
whatubinup2-4.0.0.dist-info/top_level.txt
whatubinup2-4.0.0.dist-info/RECORD
