Metadata-Version: 2.1
Name: whatubinup2
Version: 4.0.0
Summary: Python desktop client for managing time logging
Author-email: TJTH <tim@tjth.co>
Project-URL: Homepage, https://github.com/teamjtharrison/whatubinup2
Keywords: python,timelog
Requires-Python: >=3.9
Requires-Dist: PySimpleGUI (>=4.60.1)
